ai/backend/client/VERSION
ai/backend/client/__init__.py
ai/backend/client/auth.py
ai/backend/client/compat.py
ai/backend/client/config.py
ai/backend/client/exceptions.py
ai/backend/client/helper.py
ai/backend/client/load_balancing.py
ai/backend/client/pagination.py
ai/backend/client/py.typed
ai/backend/client/request.py
ai/backend/client/service.py
ai/backend/client/session.py
ai/backend/client/types.py
ai/backend/client/utils.py
ai/backend/client/versioning.py
ai/backend/client/cli/__init__.py
ai/backend/client/cli/__main__.py
ai/backend/client/cli/announcement.py
ai/backend/client/cli/app.py
ai/backend/client/cli/config.py
ai/backend/client/cli/deployment.py
ai/backend/client/cli/dotfile.py
ai/backend/client/cli/events.py
ai/backend/client/cli/extensions.py
ai/backend/client/cli/image.py
ai/backend/client/cli/logs.py
ai/backend/client/cli/main.py
ai/backend/client/cli/model.py
ai/backend/client/cli/network.py
ai/backend/client/cli/notification.py
ai/backend/client/cli/notification_utils.py
ai/backend/client/cli/pagination.py
ai/backend/client/cli/pretty.py
ai/backend/client/cli/proxy.py
ai/backend/client/cli/scheduling_history.py
ai/backend/client/cli/server_log.py
ai/backend/client/cli/service.py
ai/backend/client/cli/service_auto_scaling_rule.py
ai/backend/client/cli/session_template.py
ai/backend/client/cli/types.py
ai/backend/client/cli/vfolder.py
ai/backend/client/cli/admin/__init__.py
ai/backend/client/cli/admin/acl.py
ai/backend/client/cli/admin/agent.py
ai/backend/client/cli/admin/domain.py
ai/backend/client/cli/admin/etcd.py
ai/backend/client/cli/admin/export.py
ai/backend/client/cli/admin/group.py
ai/backend/client/cli/admin/image.py
ai/backend/client/cli/admin/keypair.py
ai/backend/client/cli/admin/license.py
ai/backend/client/cli/admin/manager.py
ai/backend/client/cli/admin/quota_scope.py
ai/backend/client/cli/admin/resource.py
ai/backend/client/cli/admin/resource_policy.py
ai/backend/client/cli/admin/scaling_group.py
backend_ai_client-26.1.0.dist-info/METADATA
backend_ai_client-26.1.0.dist-info/WHEEL
backend_ai_client-26.1.0.dist-info/entry_points.txt
backend_ai_client-26.1.0.dist-info/namespace_packages.txt
backend_ai_client-26.1.0.dist-info/top_level.txt
backend_ai_client-26.1.0.dist-info/RECORD
