Metadata-Version: 2.4
Name: backend.ai-client
Version: 26.1.0
Summary: Backend.AI Client SDK
Home-page: https://github.com/lablup/backend.ai
Author: Lablup Inc. and contributors
License: MIT
Project-URL: Documentation, https://docs.backend.ai/
Project-URL: Source, https://github.com/lablup/backend.ai
Classifier: Intended Audience :: Developers
Classifier: Operating System :: MacOS :: MacOS X
Classifier: Operating System :: POSIX :: Linux
Classifier: Programming Language :: Python
Classifier: Programming Language :: Python :: 3
Classifier: Environment :: No Input/Output (Daemon)
Classifier: Topic :: Scientific/Engineering
Classifier: Topic :: Software Development
Classifier: Development Status :: 5 - Production/Stable
Classifier: Programming Language :: Python :: 3.13
Classifier: License :: OSI Approved :: MIT License
Requires-Python: >=3.13,<3.14
Requires-Dist: aiohttp~=3.13.3
Requires-Dist: aiotusclient~=0.1.4
Requires-Dist: appdirs~=1.4.4
Requires-Dist: async_timeout~=4.0
Requires-Dist: attrs>=25.3
Requires-Dist: backend.ai-cli==26.1.0
Requires-Dist: backend.ai-common==26.1.0
Requires-Dist: backend.ai-logging==26.1.0
Requires-Dist: backend.ai-plugin==26.1.0
Requires-Dist: click~=8.1.7
Requires-Dist: faker~=24.7.1
Requires-Dist: humanize>=3.1.0
Requires-Dist: inquirer~=3.3.0
Requires-Dist: janus~=2.0
Requires-Dist: multidict~=6.6.4
Requires-Dist: pycryptodome>=3.20.0
Requires-Dist: python-dateutil>=2.9
Requires-Dist: python-dotenv~=0.20.0
Requires-Dist: rich~=13.6
Requires-Dist: tabulate~=0.8.9
Requires-Dist: tenacity>=9.0
Requires-Dist: tqdm~=4.67.1
Requires-Dist: treelib~=1.7.0
Requires-Dist: types-python-dateutil
Requires-Dist: types-tabulate
Requires-Dist: types-tqdm
Requires-Dist: yarl~=1.19.0
Dynamic: author
Dynamic: classifier
Dynamic: description
Dynamic: description-content-type
Dynamic: home-page
Dynamic: license
Dynamic: project-url
Dynamic: requires-dist
Dynamic: requires-python
Dynamic: summary
